Workbook
Name Slicer_Quarter: #N/A
Name Slicer_Region: #N/A
Name Slicer_Vendor_Name: #N/A
Name Slicer_Year: #N/A

Sheet Dashboard
B2: Spend & Cost Analysis Dashboard
B3: Full-year procurement spend by category, department and month
B5: TOTAL SPEND | E5: TOTAL ORDERS | H5: TOTAL ORDER QTY | K5: AVG SPEND / ORDER | N5: AVG SPEND / UNIT | Q5: AVG MONTHLY SPEND
B6: =Sheet2!B4 -> 12614483 | E6: =Sheet2!C4 -> 30 | H6: =Sheet2!D4 -> 461 | K6: =Sheet2!B4/Sheet2!C4 -> 420482.75 | N6: =Sheet2!B4/Sheet2!D4 -> 27363.303 | Q6: ='Dashboard Data'!I4 -> 1051206.9
B7: Full year | E7: ="Purchase orders (full year)" -> Purchase orders (full year) | H7: ="Avg "&TEXT(Sheet2!D4/Sheet2!C4,"0.0")&" units / order" -> Avg 15.4 units / order | K7: ="Total spend ÷ orders" -> Total spend ÷ orders | N7: ="Total spend ÷ order qty" -> Total spend ÷ order qty | Q7: ="Peak: "&INDEX('Dashboard Data'!B4:B15,MATCH(MAX('Dashboard Data'!D4:D15),'Dashboard Data'!D4:D15,0))&" "&TEXT(MAX('Dashboard Data'!D4:D15),"$#,##0.00,,""M""") -> Peak: March $3.76M
B9: Spend Trend & Seasonality
B29: Category & Department Mix
B49: Category Concentration
B69: Key Insights & Actions
B70: ="Supplier concentration: "&'Dashboard Data'!P4&" = "&TEXT('Dashboard Data'!R4,"0.0%") -> Supplier concentration: Raw Materials = 68.7% | G70: =TEXT('Dashboard Data'!Q4,"$#,##0.00,,""M""")&" flows into a single category. Prioritize strategic sourcing, multi-supplier contracts and price-indexation clauses to reduce exposure to commodity price swings." -> $8.66M flows into a single category. Prioritize strategic sourcing, multi-supplier contracts and price-indexation clauses to reduce exposure to commodity price swings.
B71: ="Operations drive "&TEXT(Details!C40,"0.0%")&" of spend" -> Operations drive 90.4% of spend | G71: ='Dashboard Data'!V4&" ("&TEXT('Dashboard Data'!X4,"$#,##0.00,,""M""")&") and "&'Dashboard Data'!V5&" ("&TEXT('Dashboard Data'!X5,"$#,##0.00,,""M""")&") dominate. Target cost-reduction programs here first; "&'Dashboard Data'!V6&" ("&TEXT('Dashboard Data'!W6,"0.0%")&") and "&'Dashboard Data'!V7&" ("&TEXT('Dashboard Data'!W7,"0.0%")&") are minor." -> Supply Chain ($5.88M) and Production ($5.53M) dominate. Target cost-reduction programs here first; Admin (4.8%) and IT (4.7%) are minor.
B72: ="Irregular monthly spend (CV "&TEXT(Details!C28,"0.00")&")" -> Irregular monthly spend (CV 1.24) | G72: ="Peak "&Details!C35&" vs low "&Details!C36&". The top 3 months account for "&TEXT(Details!C29,"0.0%")&" of annual spend – smooth purchasing to improve cash-flow planning." -> Peak March – $3,764,104 vs low September – $4,115. The top 3 months account for 75.3% of annual spend – smooth purchasing to improve cash-flow planning.
B73: ="Front-loaded year: H1 "&TEXT(Details!C37,"0.0%")&" vs H2 "&TEXT(Details!C38,"0.0%") -> Front-loaded year: H1 68.0% vs H2 32.0% | G73: ="Q1 alone is "&TEXT('Dashboard Data'!L4,"$#,##0.00,,""M""")&" ("&TEXT('Dashboard Data'!M4,"0.0%")&"). Q3 is the quietest quarter at "&TEXT('Dashboard Data'!L6,"$#,##0.00,,""M""")&" – use it for supplier negotiations ahead of the Q4/Q1 peak." -> Q1 alone is $7.83M (62.1%). Q3 is the quietest quarter at $1.55M – use it for supplier negotiations ahead of the Q4/Q1 peak.
B74: ="High-value, low-volume purchasing" -> High-value, low-volume purchasing | G74: =TEXT(Sheet2!C4,"0")&" orders averaging "&TEXT(K6,"$#,##0.0,""K""")&" each and "&TEXT(N6,"$#,##0.0,""K""")&" per unit. Every order is material – enforce approval workflows and competitive bids above a set threshold." -> 30 orders averaging $420.5K each and $27.4K per unit. Every order is material – enforce approval workflows and competitive bids above a set threshold.
B75: ='Dashboard Data'!P5&" is the #2 category ("&TEXT('Dashboard Data'!R5,"0.0%")&")" -> IT Equipment is the #2 category (18.9%) | G75: =TEXT('Dashboard Data'!Q5,"$#,##0.00,,""M""")&" – review asset lifecycle, lease-vs-buy options and volume agreements with preferred vendors." -> $2.39M – review asset lifecycle, lease-vs-buy options and volume agreements with preferred vendors.
B76: ='Dashboard Data'!P6&" is "&TEXT('Dashboard Data'!R6,"0.0%")&" of spend" -> Logistics is 9.5% of spend | G76: =TEXT('Dashboard Data'!Q6,"$#,##0.00,,""M""")&" – benchmark freight rates and consolidate shipments, especially around peak months." -> $1.20M – benchmark freight rates and consolidate shipments, especially around peak months.
B77: ="Tail spend is minimal ("&TEXT(Details!C41,"0.0%")&")" -> Tail spend is minimal (0.3%) | G77: ="Small categories ("&'Dashboard Data'!P8&", "&'Dashboard Data'!P9&") can be consolidated onto catalogs / P-cards to cut processing cost rather than negotiating price." -> Small categories (Packaging, Office Supplies) can be consolidated onto catalogs / P-cards to cut processing cost rather than negotiating price.
B79: Detail tables, concentration/risk indicators and key metrics are on the Details sheet; chart source data is on Dashboard Data (linked to the Sheet2 pivot tables).

Sheet Details
B2: Detail Tables, Risk Indicators & Key Metrics
B3: Supporting detail behind the Dashboard charts. All figures link to 'Dashboard Data', which links to the Sheet2 pivot tables.
B5: Monthly Spend Detail | J5: Spend by Category | P5: Spend by Department
B6: Month | C6: Quarter | D6: Spend ($) | E6: % of Annual | F6: MoM Change | G6: vs Avg | H6: Cumulative % | J6: Rank | K6: Category | L6: Spend ($) | M6: Share | N6: Cumulative % | P6: Rank | Q6: Department | R6: Spend ($) | S6: Share
B7: ='Dashboard Data'!B4 -> January | C7: ='Dashboard Data'!C4 -> Q1 | D7: ='Dashboard Data'!D4 -> 3480552.6 | E7: ='Dashboard Data'!E4 -> 0.27591719 | G7: ='Dashboard Data'!G4 -> 2.3110063 | H7: ='Dashboard Data'!H4 -> 0.27591719 | J7: ='Dashboard Data'!O4 -> 1 | K7: ='Dashboard Data'!P4 -> Raw Materials | L7: ='Dashboard Data'!Q4 -> 8664488.3 | M7: ='Dashboard Data'!R4 -> 0.68686831 | N7: ='Dashboard Data'!S4 -> 0.68686831 | P7: ='Dashboard Data'!U4 -> 1 | Q7: ='Dashboard Data'!V4 -> Supply Chain | R7: ='Dashboard Data'!X4 -> 5880295.1 | S7: ='Dashboard Data'!W4 -> 0.46615428
B8: ='Dashboard Data'!B5 -> February | C8: ='Dashboard Data'!C5 -> Q1 | D8: ='Dashboard Data'!D5 -> 584841.8 | E8: ='Dashboard Data'!E5 -> 0.046362726 | F8: ='Dashboard Data'!F5 -> -0.83196869 | G8: ='Dashboard Data'!G5 -> -0.44364729 | H8: ='Dashboard Data'!H5 -> 0.32227992 | J8: ='Dashboard Data'!O5 -> 2 | K8: ='Dashboard Data'!P5 -> IT Equipment | L8: ='Dashboard Data'!Q5 -> 2386315.3 | M8: ='Dashboard Data'!R5 -> 0.18917267 | N8: ='Dashboard Data'!S5 -> 0.87604098 | P8: ='Dashboard Data'!U5 -> 2 | Q8: ='Dashboard Data'!V5 -> Production | R8: ='Dashboard Data'!X5 -> 5528617.8 | S8: ='Dashboard Data'!W5 -> 0.43827543
B9: ='Dashboard Data'!B6 -> March | C9: ='Dashboard Data'!C6 -> Q1 | D9: ='Dashboard Data'!D6 -> 3764104.5 | E9: ='Dashboard Data'!E6 -> 0.29839547 | F9: ='Dashboard Data'!F6 -> 5.4361071 | G9: ='Dashboard Data'!G6 -> 2.5807456 | H9: ='Dashboard Data'!H6 -> 0.62067538 | J9: ='Dashboard Data'!O6 -> 3 | K9: ='Dashboard Data'!P6 -> Logistics | L9: ='Dashboard Data'!Q6 -> 1197774.2 | M9: ='Dashboard Data'!R6 -> 0.094952307 | N9: ='Dashboard Data'!S6 -> 0.97099328 | P9: ='Dashboard Data'!U6 -> 3 | Q9: ='Dashboard Data'!V6 -> Admin | R9: ='Dashboard Data'!X6 -> 610542.52 | S9: ='Dashboard Data'!W6 -> 0.048400124
B10: ='Dashboard Data'!B7 -> April | C10: ='Dashboard Data'!C7 -> Q2 | D10: ='Dashboard Data'!D7 -> 129550.41 | E10: ='Dashboard Data'!E7 -> 0.010269974 | F10: ='Dashboard Data'!F7 -> -0.96558267 | G10: ='Dashboard Data'!G7 -> -0.87676031 | H10: ='Dashboard Data'!H7 -> 0.63094536 | J10: ='Dashboard Data'!O7 -> 4 | K10: ='Dashboard Data'!P7 -> MRO | L10: ='Dashboard Data'!Q7 -> 329113.49 | M10: ='Dashboard Data'!R7 -> 0.02609013 | N10: ='Dashboard Data'!S7 -> 0.99708341 | P10: ='Dashboard Data'!U7 -> 4 | Q10: ='Dashboard Data'!V7 -> IT | R10: ='Dashboard Data'!X7 -> 595027.14 | S10: ='Dashboard Data'!W7 -> 0.047170158
B11: ='Dashboard Data'!B8 -> May | C11: ='Dashboard Data'!C8 -> Q2 | D11: ='Dashboard Data'!D8 -> 454227.3 | E11: ='Dashboard Data'!E8 -> 0.036008397 | F11: ='Dashboard Data'!F8 -> 2.5061819 | G11: ='Dashboard Data'!G8 -> -0.56789923 | H11: ='Dashboard Data'!H8 -> 0.66695376 | J11: ='Dashboard Data'!O8 -> 5 | K11: ='Dashboard Data'!P8 -> Packaging | L11: ='Dashboard Data'!Q8 -> 20395.74 | M11: ='Dashboard Data'!R8 -> 0.0016168511 | N11: ='Dashboard Data'!S8 -> 0.99870026 | Q11: Total | R11: ='Dashboard Data'!X8 -> 12614483 | S11: ='Dashboard Data'!W8 -> 1
B12: ='Dashboard Data'!B9 -> June | C12: ='Dashboard Data'!C9 -> Q2 | D12: ='Dashboard Data'!D9 -> 158629.15 | E12: ='Dashboard Data'!E9 -> 0.012575161 | F12: ='Dashboard Data'!F9 -> -0.65077143 | G12: ='Dashboard Data'!G9 -> -0.84909807 | H12: ='Dashboard Data'!H9 -> 0.67952892 | J12: ='Dashboard Data'!O9 -> 6 | K12: ='Dashboard Data'!P9 -> Office Supplies | L12: ='Dashboard Data'!Q9 -> 16395.5 | M12: ='Dashboard Data'!R9 -> 0.0012997362 | N12: ='Dashboard Data'!S9 -> 1
B13: ='Dashboard Data'!B10 -> July | C13: ='Dashboard Data'!C10 -> Q3 | D13: ='Dashboard Data'!D10 -> 278027.78 | E13: ='Dashboard Data'!E10 -> 0.022040363 | F13: ='Dashboard Data'!F10 -> 0.75269035 | G13: ='Dashboard Data'!G10 -> -0.73551564 | H13: ='Dashboard Data'!H10 -> 0.70156928 | K13: Total | L13: ='Dashboard Data'!Q10 -> 12614483 | M13: ='Dashboard Data'!R10 -> 1
B14: ='Dashboard Data'!B11 -> August | C14: ='Dashboard Data'!C11 -> Q3 | D14: ='Dashboard Data'!D11 -> 1265283.9 | E14: ='Dashboard Data'!E11 -> 0.10030406 | F14: ='Dashboard Data'!F11 -> 3.5509261 | G14: ='Dashboard Data'!G11 -> 0.20364877 | H14: ='Dashboard Data'!H11 -> 0.80187334
B15: ='Dashboard Data'!B12 -> September | C15: ='Dashboard Data'!C12 -> Q3 | D15: ='Dashboard Data'!D12 -> 4115.44 | E15: ='Dashboard Data'!E12 -> 0.00032624723 | F15: ='Dashboard Data'!F12 -> -0.99674742 | G15: ='Dashboard Data'!G12 -> -0.99608503 | H15: ='Dashboard Data'!H12 -> 0.80219959
B16: ='Dashboard Data'!B13 -> October | C16: ='Dashboard Data'!C13 -> Q4 | D16: ='Dashboard Data'!D13 -> 10323.74 | E16: ='Dashboard Data'!E13 -> 0.00081840376 | F16: ='Dashboard Data'!F13 -> 1.5085386 | G16: ='Dashboard Data'!G13 -> -0.99017915 | H16: ='Dashboard Data'!H13 -> 0.803018
B17: ='Dashboard Data'!B14 -> November | C17: ='Dashboard Data'!C14 -> Q4 | D17: ='Dashboard Data'!D14 -> 231048.54 | E17: ='Dashboard Data'!E14 -> 0.018316133 | F17: ='Dashboard Data'!F14 -> 21.380314 | G17: ='Dashboard Data'!G14 -> -0.78020641 | H17: ='Dashboard Data'!H14 -> 0.82133413
B18: ='Dashboard Data'!B15 -> December | C18: ='Dashboard Data'!C15 -> Q4 | D18: ='Dashboard Data'!D15 -> 2253777.5 | E18: ='Dashboard Data'!E15 -> 0.17866587 | F18: ='Dashboard Data'!F15 -> 8.754563 | G18: ='Dashboard Data'!G15 -> 1.1439905 | H18: ='Dashboard Data'!H15 -> 1
B19: Total | D19: ='Dashboard Data'!D16 -> 12614483 | E19: ='Dashboard Data'!E16 -> 1
B22: Concentration & Risk Indicators
B23: Risk Indicator | C23: Value | D23: Medium ≥ | E23: High ≥ | F23: Risk Level
B24: ="Top category share ("&'Dashboard Data'!P4&")" -> Top category share (Raw Materials) | C24: ='Dashboard Data'!R4 -> 0.68686831 | D24: 0.4 | E24: 0.6 | F24: =IF(C24>=E24,"High",IF(C24>=D24,"Medium","Low")) -> High
B25: Top-3 category share | C25: ='Dashboard Data'!S6 -> 0.97099328 | D25: 0.8 | E25: 0.9 | F25: =IF(C25>=E25,"High",IF(C25>=D25,"Medium","Low")) -> High
B26: Category concentration (HHI) | C26: {=SUMPRODUCT(('Dashboard Data'!R4:R9*100)^2)} -> 5172.7531 | D26: 1500 | E26: 2500 | F26: =IF(C26>=E26,"High",IF(C26>=D26,"Medium","Low")) -> High
B27: Department concentration (HHI) | C27: {=SUMPRODUCT(('Dashboard Data'!W4:W7*100)^2)} -> 4139.5277 | D27: 1500 | E27: 2500 | F27: =IF(C27>=E27,"High",IF(C27>=D27,"Medium","Low")) -> High
B28: Monthly volatility (coeff. of variation) | C28: =_xlfn.STDEV.P('Dashboard Data'!D4:D15)/AVERAGE('Dashboard Data'!D4:D15) -> 1.2410526 | D28: 0.5 | E28: 1 | F28: =IF(C28>=E28,"High",IF(C28>=D28,"Medium","Low")) -> High
B29: Top-3 months share of annual spend | C29: {=SUM(LARGE('Dashboard Data'!D4:D15,{1,2,3}))/'Dashboard Data'!D16} -> 0.75297853 | D29: 0.5 | E29: 0.7 | F29: =IF(C29>=E29,"High",IF(C29>=D29,"Medium","Low")) -> High
B30: HHI above 2,500 = highly concentrated. CV above 1 = irregular spend.
B33: Key Metrics
B34: Key Metric | C34: Value
B35: Peak month | C35: =INDEX('Dashboard Data'!B4:B15,MATCH(MAX('Dashboard Data'!D4:D15),'Dashboard Data'!D4:D15,0))&" – "&TEXT(MAX('Dashboard Data'!D4:D15),"$#,##0") -> March – $3,764,104
B36: Lowest month | C36: =INDEX('Dashboard Data'!B4:B15,MATCH(MIN('Dashboard Data'!D4:D15),'Dashboard Data'!D4:D15,0))&" – "&TEXT(MIN('Dashboard Data'!D4:D15),"$#,##0") -> September – $4,115
B37: H1 share of spend (Jan–Jun) | C37: =SUM('Dashboard Data'!D4:D9)/'Dashboard Data'!D16 -> 0.67952892
B38: H2 share of spend (Jul–Dec) | C38: =SUM('Dashboard Data'!D10:D15)/'Dashboard Data'!D16 -> 0.32047108
B39: Q1 share of spend | C39: ='Dashboard Data'!M4 -> 0.62067538
B40: Operations share (Supply Chain + Production) | C40: =SUMIFS('Dashboard Data'!W4:W7,'Dashboard Data'!V4:V7,"Supply Chain")+SUMIFS('Dashboard Data'!W4:W7,'Dashboard Data'!V4:V7,"Production") -> 0.90442972
B41: Tail spend (categories < 1% each) | C41: =SUMIFS('Dashboard Data'!R4:R9,'Dashboard Data'!R4:R9,"<0.01") -> 0.0029165873

Sheet Sheet2
B3: Total Spend | C3: Total Order | D3: Total Order QTY | E3: Avg. Order QTY | F3: Per Order Vlue | I3: Department Name | J3: Total Spend | L3: Category | M3: Total Spend | Q3: Month Number | R3: Month Name | S3: Total Spend
B4: 12614483 | C4: 30 | D4: 461 | E4: 15.366667 | F4: 27363.303 | I4: Admin | J4: 0.048400124 | L4: IT Equipment | M4: 2386315.3 | Q4: 1 | R4: January | S4: 3480552.6
I5: IT | J5: 0.047170158 | L5: Logistics | M5: 1197774.2 | Q5: 2 | R5: February | S5: 584841.8
I6: Production | J6: 0.43827543 | L6: MRO | M6: 329113.49 | Q6: 3 | R6: March | S6: 3764104.5
I7: Supply Chain | J7: 0.46615428 | L7: Office Supplies | M7: 16395.5 | Q7: 4 | R7: April | S7: 129550.41
I8: Grand Total | J8: 1 | L8: Packaging | M8: 20395.74 | Q8: 5 | R8: May | S8: 454227.3
L9: Raw Materials | M9: 8664488.3 | Q9: 6 | R9: June | S9: 158629.15
L10: Grand Total | M10: 12614483 | Q10: 7 | R10: July | S10: 278027.78
Q11: 8 | R11: August | S11: 1265283.9
Q12: 9 | R12: September | S12: 4115.44
Q13: 10 | R13: October | S13: 10323.74
Q14: 11 | R14: November | S14: 231048.54
Q15: 12 | R15: December | S15: 2253777.5
Q16: Grand Total | S16: 12614483

Sheet Dashboard Data
A1: Dashboard Data – calculations feeding the Dashboard sheet (all linked to Sheet2)
A3: Month | B3: Month Name | C3: Quarter | D3: Spend ($) | E3: % of Annual | F3: MoM Change | G3: vs Avg | H3: Cumulative % | I3: Monthly Avg | K3: Quarter | L3: Spend ($) | M3: Share | O3: Rank | P3: Category | Q3: Spend ($) | R3: Share | S3: Cumulative % | U3: Rank | V3: Department | W3: Share | X3: Spend ($)
A4: =LEFT(Sheet2!R4,3) -> Jan | B4: =Sheet2!R4 -> January | C4: ="Q"&ROUNDUP(Sheet2!Q4/3,0) -> Q1 | D4: =Sheet2!S4 -> 3480552.6 | E4: =D4/$D$16 -> 0.27591719 | G4: =D4/$I4-1 -> 2.3110063 | H4: =SUM($D$4:D4)/$D$16 -> 0.27591719 | I4: =AVERAGE($D$4:$D$15) -> 1051206.9 | K4: Q1 | L4: =SUMIFS($D$4:$D$15,$C$4:$C$15,K4) -> 7829498.8 | M4: =L4/$L$8 -> 0.62067538 | O4: 1 | P4: =INDEX(Sheet2!$L$4:$L$9,MATCH(Q4,Sheet2!$M$4:$M$9,0)) -> Raw Materials | Q4: =LARGE(Sheet2!$M$4:$M$9,O4) -> 8664488.3 | R4: =Q4/Sheet2!$M$10 -> 0.68686831 | S4: =SUM($R$4:R4) -> 0.68686831 | U4: 1 | V4: =INDEX(Sheet2!$I$4:$I$7,MATCH(W4,Sheet2!$J$4:$J$7,0)) -> Supply Chain | W4: =LARGE(Sheet2!$J$4:$J$7,U4) -> 0.46615428 | X4: =W4*Sheet2!$B$4 -> 5880295.1
A5: =LEFT(Sheet2!R5,3) -> Feb | B5: =Sheet2!R5 -> February | C5: ="Q"&ROUNDUP(Sheet2!Q5/3,0) -> Q1 | D5: =Sheet2!S5 -> 584841.8 | E5: =D5/$D$16 -> 0.046362726 | F5: =D5/D4-1 -> -0.83196869 | G5: =D5/$I5-1 -> -0.44364729 | H5: =SUM($D$4:D5)/$D$16 -> 0.32227992 | I5: =AVERAGE($D$4:$D$15) -> 1051206.9 | K5: Q2 | L5: =SUMIFS($D$4:$D$15,$C$4:$C$15,K5) -> 742406.86 | M5: =L5/$L$8 -> 0.058853532 | O5: 2 | P5: =INDEX(Sheet2!$L$4:$L$9,MATCH(Q5,Sheet2!$M$4:$M$9,0)) -> IT Equipment | Q5: =LARGE(Sheet2!$M$4:$M$9,O5) -> 2386315.3 | R5: =Q5/Sheet2!$M$10 -> 0.18917267 | S5: =SUM($R$4:R5) -> 0.87604098 | U5: 2 | V5: =INDEX(Sheet2!$I$4:$I$7,MATCH(W5,Sheet2!$J$4:$J$7,0)) -> Production | W5: =LARGE(Sheet2!$J$4:$J$7,U5) -> 0.43827543 | X5: =W5*Sheet2!$B$4 -> 5528617.8
A6: =LEFT(Sheet2!R6,3) -> Mar | B6: =Sheet2!R6 -> March | C6: ="Q"&ROUNDUP(Sheet2!Q6/3,0) -> Q1 | D6: =Sheet2!S6 -> 3764104.5 | E6: =D6/$D$16 -> 0.29839547 | F6: =D6/D5-1 -> 5.4361071 | G6: =D6/$I6-1 -> 2.5807456 | H6: =SUM($D$4:D6)/$D$16 -> 0.62067538 | I6: =AVERAGE($D$4:$D$15) -> 1051206.9 | K6: Q3 | L6: =SUMIFS($D$4:$D$15,$C$4:$C$15,K6) -> 1547427.1 | M6: =L6/$L$8 -> 0.12267067 | O6: 3 | P6: =INDEX(Sheet2!$L$4:$L$9,MATCH(Q6,Sheet2!$M$4:$M$9,0)) -> Logistics | Q6: =LARGE(Sheet2!$M$4:$M$9,O6) -> 1197774.2 | R6: =Q6/Sheet2!$M$10 -> 0.094952307 | S6: =SUM($R$4:R6) -> 0.97099328 | U6: 3 | V6: =INDEX(Sheet2!$I$4:$I$7,MATCH(W6,Sheet2!$J$4:$J$7,0)) -> Admin | W6: =LARGE(Sheet2!$J$4:$J$7,U6) -> 0.048400124 | X6: =W6*Sheet2!$B$4 -> 610542.52
A7: =LEFT(Sheet2!R7,3) -> Apr | B7: =Sheet2!R7 -> April | C7: ="Q"&ROUNDUP(Sheet2!Q7/3,0) -> Q2 | D7: =Sheet2!S7 -> 129550.41 | E7: =D7/$D$16 -> 0.010269974 | F7: =D7/D6-1 -> -0.96558267 | G7: =D7/$I7-1 -> -0.87676031 | H7: =SUM($D$4:D7)/$D$16 -> 0.63094536 | I7: =AVERAGE($D$4:$D$15) -> 1051206.9 | K7: Q4 | L7: =SUMIFS($D$4:$D$15,$C$4:$C$15,K7) -> 2495149.8 | M7: =L7/$L$8 -> 0.19780041 | O7: 4 | P7: =INDEX(Sheet2!$L$4:$L$9,MATCH(Q7,Sheet2!$M$4:$M$9,0)) -> MRO | Q7: =LARGE(Sheet2!$M$4:$M$9,O7) -> 329113.49 | R7: =Q7/Sheet2!$M$10 -> 0.02609013 | S7: =SUM($R$4:R7) -> 0.99708341 | U7: 4 | V7: =INDEX(Sheet2!$I$4:$I$7,MATCH(W7,Sheet2!$J$4:$J$7,0)) -> IT | W7: =LARGE(Sheet2!$J$4:$J$7,U7) -> 0.047170158 | X7: =W7*Sheet2!$B$4 -> 595027.14
A8: =LEFT(Sheet2!R8,3) -> May | B8: =Sheet2!R8 -> May | C8: ="Q"&ROUNDUP(Sheet2!Q8/3,0) -> Q2 | D8: =Sheet2!S8 -> 454227.3 | E8: =D8/$D$16 -> 0.036008397 | F8: =D8/D7-1 -> 2.5061819 | G8: =D8/$I8-1 -> -0.56789923 | H8: =SUM($D$4:D8)/$D$16 -> 0.66695376 | I8: =AVERAGE($D$4:$D$15) -> 1051206.9 | K8: Total | L8: =SUM(L4:L7) -> 12614483 | M8: =SUM(M4:M7) -> 1 | O8: 5 | P8: =INDEX(Sheet2!$L$4:$L$9,MATCH(Q8,Sheet2!$M$4:$M$9,0)) -> Packaging | Q8: =LARGE(Sheet2!$M$4:$M$9,O8) -> 20395.74 | R8: =Q8/Sheet2!$M$10 -> 0.0016168511 | S8: =SUM($R$4:R8) -> 0.99870026 | V8: Total | W8: =SUM(W4:W7) -> 1 | X8: =SUM(X4:X7) -> 12614483
A9: =LEFT(Sheet2!R9,3) -> Jun | B9: =Sheet2!R9 -> June | C9: ="Q"&ROUNDUP(Sheet2!Q9/3,0) -> Q2 | D9: =Sheet2!S9 -> 158629.15 | E9: =D9/$D$16 -> 0.012575161 | F9: =D9/D8-1 -> -0.65077143 | G9: =D9/$I9-1 -> -0.84909807 | H9: =SUM($D$4:D9)/$D$16 -> 0.67952892 | I9: =AVERAGE($D$4:$D$15) -> 1051206.9 | O9: 6 | P9: =INDEX(Sheet2!$L$4:$L$9,MATCH(Q9,Sheet2!$M$4:$M$9,0)) -> Office Supplies | Q9: =LARGE(Sheet2!$M$4:$M$9,O9) -> 16395.5 | R9: =Q9/Sheet2!$M$10 -> 0.0012997362 | S9: =SUM($R$4:R9) -> 1
A10: =LEFT(Sheet2!R10,3) -> Jul | B10: =Sheet2!R10 -> July | C10: ="Q"&ROUNDUP(Sheet2!Q10/3,0) -> Q3 | D10: =Sheet2!S10 -> 278027.78 | E10: =D10/$D$16 -> 0.022040363 | F10: =D10/D9-1 -> 0.75269035 | G10: =D10/$I10-1 -> -0.73551564 | H10: =SUM($D$4:D10)/$D$16 -> 0.70156928 | I10: =AVERAGE($D$4:$D$15) -> 1051206.9 | P10: Total | Q10: =SUM(Q4:Q9) -> 12614483 | R10: =SUM(R4:R9) -> 1
A11: =LEFT(Sheet2!R11,3) -> Aug | B11: =Sheet2!R11 -> August | C11: ="Q"&ROUNDUP(Sheet2!Q11/3,0) -> Q3 | D11: =Sheet2!S11 -> 1265283.9 | E11: =D11/$D$16 -> 0.10030406 | F11: =D11/D10-1 -> 3.5509261 | G11: =D11/$I11-1 -> 0.20364877 | H11: =SUM($D$4:D11)/$D$16 -> 0.80187334 | I11: =AVERAGE($D$4:$D$15) -> 1051206.9
A12: =LEFT(Sheet2!R12,3) -> Sep | B12: =Sheet2!R12 -> September | C12: ="Q"&ROUNDUP(Sheet2!Q12/3,0) -> Q3 | D12: =Sheet2!S12 -> 4115.44 | E12: =D12/$D$16 -> 0.00032624723 | F12: =D12/D11-1 -> -0.99674742 | G12: =D12/$I12-1 -> -0.99608503 | H12: =SUM($D$4:D12)/$D$16 -> 0.80219959 | I12: =AVERAGE($D$4:$D$15) -> 1051206.9
A13: =LEFT(Sheet2!R13,3) -> Oct | B13: =Sheet2!R13 -> October | C13: ="Q"&ROUNDUP(Sheet2!Q13/3,0) -> Q4 | D13: =Sheet2!S13 -> 10323.74 | E13: =D13/$D$16 -> 0.00081840376 | F13: =D13/D12-1 -> 1.5085386 | G13: =D13/$I13-1 -> -0.99017915 | H13: =SUM($D$4:D13)/$D$16 -> 0.803018 | I13: =AVERAGE($D$4:$D$15) -> 1051206.9
A14: =LEFT(Sheet2!R14,3) -> Nov | B14: =Sheet2!R14 -> November | C14: ="Q"&ROUNDUP(Sheet2!Q14/3,0) -> Q4 | D14: =Sheet2!S14 -> 231048.54 | E14: =D14/$D$16 -> 0.018316133 | F14: =D14/D13-1 -> 21.380314 | G14: =D14/$I14-1 -> -0.78020641 | H14: =SUM($D$4:D14)/$D$16 -> 0.82133413 | I14: =AVERAGE($D$4:$D$15) -> 1051206.9
A15: =LEFT(Sheet2!R15,3) -> Dec | B15: =Sheet2!R15 -> December | C15: ="Q"&ROUNDUP(Sheet2!Q15/3,0) -> Q4 | D15: =Sheet2!S15 -> 2253777.5 | E15: =D15/$D$16 -> 0.17866587 | F15: =D15/D14-1 -> 8.754563 | G15: =D15/$I15-1 -> 1.1439905 | H15: =SUM($D$4:D15)/$D$16 -> 1 | I15: =AVERAGE($D$4:$D$15) -> 1051206.9
A16: Total | D16: =SUM(D4:D15) -> 12614483 | E16: =SUM(E4:E15) -> 1
A19: Chart feeds – contiguous ranges used as chart source data
A21: Month | B21: Monthly spend | C21: Monthly average | E21: Quarter | F21: Spend ($) | H21: Category | I21: Spend ($) | K21: Department | L21: Spend ($) | N21: Category | O21: Share of spend | P21: Cumulative %
A22: =A4 -> Jan | B22: =D4 -> 3480552.6 | C22: =$I$4 -> 1051206.9 | E22: =K4 -> Q1 | F22: =L4 -> 7829498.8 | H22: =P9 -> Office Supplies | I22: =Q9 -> 16395.5 | K22: =V4 -> Supply Chain | L22: =X4 -> 5880295.1 | N22: =P4 -> Raw Materials | O22: =R4 -> 0.68686831 | P22: =S4 -> 0.68686831
A23: =A5 -> Feb | B23: =D5 -> 584841.8 | C23: =$I$4 -> 1051206.9 | E23: =K5 -> Q2 | F23: =L5 -> 742406.86 | H23: =P8 -> Packaging | I23: =Q8 -> 20395.74 | K23: =V5 -> Production | L23: =X5 -> 5528617.8 | N23: =P5 -> IT Equipment | O23: =R5 -> 0.18917267 | P23: =S5 -> 0.87604098
A24: =A6 -> Mar | B24: =D6 -> 3764104.5 | C24: =$I$4 -> 1051206.9 | E24: =K6 -> Q3 | F24: =L6 -> 1547427.1 | H24: =P7 -> MRO | I24: =Q7 -> 329113.49 | K24: =V6 -> Admin | L24: =X6 -> 610542.52 | N24: =P6 -> Logistics | O24: =R6 -> 0.094952307 | P24: =S6 -> 0.97099328
A25: =A7 -> Apr | B25: =D7 -> 129550.41 | C25: =$I$4 -> 1051206.9 | E25: =K7 -> Q4 | F25: =L7 -> 2495149.8 | H25: =P6 -> Logistics | I25: =Q6 -> 1197774.2 | K25: =V7 -> IT | L25: =X7 -> 595027.14 | N25: =P7 -> MRO | O25: =R7 -> 0.02609013 | P25: =S7 -> 0.99708341
A26: =A8 -> May | B26: =D8 -> 454227.3 | C26: =$I$4 -> 1051206.9 | H26: =P5 -> IT Equipment | I26: =Q5 -> 2386315.3 | N26: =P8 -> Packaging | O26: =R8 -> 0.0016168511 | P26: =S8 -> 0.99870026
A27: =A9 -> Jun | B27: =D9 -> 158629.15 | C27: =$I$4 -> 1051206.9 | H27: =P4 -> Raw Materials | I27: =Q4 -> 8664488.3 | N27: =P9 -> Office Supplies | O27: =R9 -> 0.0012997362 | P27: =S9 -> 1
A28: =A10 -> Jul | B28: =D10 -> 278027.78 | C28: =$I$4 -> 1051206.9
A29: =A11 -> Aug | B29: =D11 -> 1265283.9 | C29: =$I$4 -> 1051206.9
A30: =A12 -> Sep | B30: =D12 -> 4115.44 | C30: =$I$4 -> 1051206.9
A31: =A13 -> Oct | B31: =D13 -> 10323.74 | C31: =$I$4 -> 1051206.9
A32: =A14 -> Nov | B32: =D14 -> 231048.54 | C32: =$I$4 -> 1051206.9
A33: =A15 -> Dec | B33: =D15 -> 2253777.5 | C33: =$I$4 -> 1051206.9
